sudachidict_full/__init__.py
SudachiDict_full-0.0.0.dist-info/LICENSE-2.0.txt
SudachiDict_full-0.0.0.dist-info/METADATA
SudachiDict_full-0.0.0.dist-info/WHEEL
SudachiDict_full-0.0.0.dist-info/top_level.txt
SudachiDict_full-0.0.0.dist-info/RECORD
