Metadata-Version: 2.1
Name: SudachiDict-full
Version: 0.0.0
Summary: A lexicon for Sudachi, the Japanese Morphological Analyzer
Home-page: https://github.com/WorksApplications/SudachiDict
Author: Works Applications Co.,Ltd.
Author-email: takaoka_k@worksap.co.jp
License: Apache-2.0
Platform: UNKNOWN
Requires-Dist: SudachiPy (>=0.2.1)
